pinpoint/__init__.py
pinpoint/exception.py
pinpoint/mail_service.py
pinpoint/sms_service.py
PinPointClient-0.0.10.dist-info/LICENSE
PinPointClient-0.0.10.dist-info/METADATA
PinPointClient-0.0.10.dist-info/WHEEL
PinPointClient-0.0.10.dist-info/top_level.txt
PinPointClient-0.0.10.dist-info/RECORD
