Metadata-Version: 2.1
Name: PinPointClient
Version: 0.0.10
Summary: PinPoint Aws Pinpoint SMS/Mail Client Python package
Home-page: https://github.com/blueromans/PinPointClient.git
Author: Yaşar Özyurt
Author-email: blueromans@gmail.com
Project-URL: Bug Tracker, https://github.com/blueromans/PinPointClient/issues
Classifier: Programming Language :: Python :: 3
Classifier: License :: OSI Approved :: MIT License
Classifier: Operating System :: OS Independent
Requires-Python: >=3.6
License-File: LICENSE
Requires-Dist: boto3
